lhcli/__init__.py
lhcli/__main__.py
lhcli/cli.py
lhcli/version.py
lhcli-0.1.0.dist-info/licenses/LICENSE
lhcli-0.1.0.dist-info/METADATA
lhcli-0.1.0.dist-info/WHEEL
lhcli-0.1.0.dist-info/entry_points.txt
lhcli-0.1.0.dist-info/top_level.txt
lhcli-0.1.0.dist-info/RECORD
