Metadata-Version: 2.4
Name: lhcli
Version: 0.1.0
Summary: LightHope CLI Tools - Enterprise Developer Tools
Author-email: William Policy <william@lighthope.com>
License-Expression: MIT
Project-URL: Homepage, https://github.com/williampolicy/lhcli
Project-URL: Repository, https://github.com/williampolicy/lhcli
Requires-Python: >=3.10
License-File: LICENSE
Requires-Dist: click>=8.1.0
Requires-Dist: rich>=13.0.0
Requires-Dist: pyyaml>=6.0
Dynamic: license-file
